dovado_rtl/__init__.py
dovado_rtl/boxers/__init__.py
dovado_rtl/boxers/boxer.py
dovado_rtl/boxers/verilog/__init__.py
dovado_rtl/boxers/verilog/box_frame.sv
dovado_rtl/boxers/verilog/boxer.py
dovado_rtl/boxers/vhdl/__init__.py
dovado_rtl/boxers/vhdl/box_frame.vhd
dovado_rtl/boxers/vhdl/boxer.py
dovado_rtl/builders/__init__.py
dovado_rtl/builders/builder.py
dovado_rtl/builders/vivado/__init__.py
dovado_rtl/builders/vivado/builder.py
dovado_rtl/builders/vivado/constraint_files/__init__.py
dovado_rtl/builders/vivado/constraint_files/constraint_frame.xdc
dovado_rtl/builders/vivado/directives.py
dovado_rtl/builders/vivado/tcl_scripts/__init__.py
dovado_rtl/builders/vivado/tcl_scripts/implementation_frame.tcl
dovado_rtl/builders/vivado/tcl_scripts/synthesis_frame.tcl
dovado_rtl/builders/vivado/vivado.py
dovado_rtl/explorers/__init__.py
dovado_rtl/explorers/automatic_explorer.py
dovado_rtl/explorers/explorer.py
dovado_rtl/explorers/manual_explorer.py
dovado_rtl/explorers/utilities/__init__.py
dovado_rtl/explorers/utilities/design_points.py
dovado_rtl/explorers/utilities/range.py
dovado_rtl/explorers/utilities/spaces.py
dovado_rtl/explorers/utilities/tasks.py
dovado_rtl/fill.py
dovado_rtl/generators/__init__.py
dovado_rtl/generators/bash_generator.py
dovado_rtl/generators/generator.py
dovado_rtl/generators/vitis/__init__.py
dovado_rtl/generators/vitis/csynth.tcl
dovado_rtl/generators/vitis/generator.py
dovado_rtl/input.py
dovado_rtl/main.py
dovado_rtl/nacolla/__init__.py
dovado_rtl/nacolla/flows/__init__.py
dovado_rtl/nacolla/flows/automatic_chisel_vivado.toml
dovado_rtl/nacolla/flows/automatic_hls_vitis.toml
dovado_rtl/nacolla/flows/automatic_system_verilog_vivado.toml
dovado_rtl/nacolla/flows/automatic_verilog_vivado.toml
dovado_rtl/nacolla/flows/automatic_vhdl_vivado.toml
dovado_rtl/nacolla/flows/manual_chisel_vivado.toml
dovado_rtl/nacolla/flows/manual_hls_vitis.toml
dovado_rtl/nacolla/flows/manual_system_verilog_vivado.toml
dovado_rtl-0.10.12.dist-info/LICENSE
dovado_rtl-0.10.12.dist-info/METADATA
dovado_rtl-0.10.12.dist-info/WHEEL
dovado_rtl-0.10.12.dist-info/entry_points.txt
dovado_rtl-0.10.12.dist-info/RECORD
