Metadata-Version: 2.1
Name: dovado-rtl
Version: 0.10.12
Summary: RTL Design Space Exploration on top of Vivado
Home-page: https://github.com/DPaletti/dovado
License: MIT
Keywords: Xilinx,Vivado,TCL,VHDL,Verilog,RTL,Design Space,Genetic Algorithm
Author: Daniele Paletti
Author-email: danielepaletti98@gmail.com
Requires-Python: >=3.9,<4.0
Classifier: License :: OSI Approved :: MIT License
Classifier: Programming Language :: Python :: 3
Classifier: Programming Language :: Python :: 3.9
Classifier: Programming Language :: Python :: 3.10
Classifier: Programming Language :: Python :: 3.11
Requires-Dist: BeautifulSoup4 (>=4.9.1,<5.0.0)
Requires-Dist: antlr4-python3-runtime (==4.11.1)
Requires-Dist: dataclasses (>=0.8,<0.9) ; python_version >= "3.6" and python_version < "3.7"
Requires-Dist: importlib-resources (>=5.1.4,<6.0.0)
Requires-Dist: lxml (>=4.5.2,<5.0.0)
Requires-Dist: movado (==0.7.4)
Requires-Dist: nacolla (==0.1.5)
Requires-Dist: numpy (==1.23.4)
Requires-Dist: pathvalidate (>=2.3.0,<3.0.0)
Requires-Dist: pexpect (>=4.8.0,<5.0.0)
Requires-Dist: pymoo (>=0.5.0,<0.6.0)
Requires-Dist: pyyaml (>=5.3.1,<6.0.0)
Requires-Dist: typer (>=0.3.2,<0.4.0)
Project-URL: Repository, https://github.com/DPaletti/dovado
